{
  "pools": [
    {
      "id": "aicc-defai",
      "name": "AICC/DEFAI",
      "token0": "AICC",
      "token1": "DEFAI",
      "tvl": 0,
      "apr": 0
    },
    {
        "id": "eliza-defai",
        "name": "ELIZA/DEFAI",
        "token0": "ELIZA",
        "token1": "DEFAI",
        "tvl": 0,
        "apr": 0
      },
    {
      "id": "defai-anon",
      "name": "DEFAI/ANON",
      "token0": "DEFAI",
      "token1": "ANON",
      "tvl": 0,
      "apr": 0
    },
    {
      "id": "defai-ai16z",
      "name": "DEFAI/AI16Z",
      "token0": "DEFAI",
      "token1": "AI16Z",
      "tvl": 0,
      "apr": 0
    },
    {
      "id": "sol-defai",
      "name": "SOL/DEFAI",
      "token0": "SOL",
      "token1": "DEFAI",
      "tvl": 0,
      "apr": 0
    },
    {
      "id": "defai-tank",
      "name": "DEFAI/TANK",
      "token0": "DEFAI",
      "token1": "TANK",
      "tvl": 0,
      "apr": 0
    },
    {
      "id": "defai-animonica",
      "name": "DEFAI/ANIMONICA",
      "token0": "DEFAI",
      "token1": "ANIMONICA",
      "tvl": 0,
      "apr": 0
    },
    {
      "id": "defai-project89",
      "name": "DEFAI/P89",
      "token0": "DEFAI",
      "token1": "P89",
      "tvl": 0,
      "apr": 0
    },
    {
      "id": "defai-afi",
      "name": "DEFAI/AFI",
      "token0": "DEFAI",
      "token1": "AFI",
      "tvl": 0,
      "apr": 0
    },
    {
      "id": "defai-shaw",
      "name": "DEFAI/SHAW",
      "token0": "DEFAI",
      "token1": "SHAW",
      "tvl": 0,
      "apr": 0
    },
    {
      "id": "defai-alice",
      "name": "DEFAI/ALICE",
      "token0": "DEFAI",
      "token1": "ALICE",
      "tvl": 0,
      "apr": 0
    },
    {
      "id": "pengu-defai",
      "name": "PENGU/DEFAI",
      "token0": "PENGU",
      "token1": "DEFAI",
      "tvl": 0,
      "apr": 0
    },
    {
      "id": "ai16z-eliza",
      "name": "AI16Z/ELIZA",
      "token0": "AI16Z",
      "token1": "ELIZA",
      "tvl": 0,
      "apr": 0
    },
    {
      "id": "ai16z-degenai",
      "name": "AI16Z/DEGENAI",
      "token0": "AI16Z",
      "token1": "DEGENAI",
      "tvl": 0,
      "apr": 0
    },
    {
      "id": "eliza-degenai",
      "name": "ELIZA/DEGENAI",
      "token0": "ELIZA",
      "token1": "DEGENAI",
      "tvl": 0,
      "apr": 0
    },
    {
      "id": "defai-aioraai",
      "name": "DEFAI/AIORAAI",
      "token0": "DEFAI",
      "token1": "AIORAAI",
      "tvl": 0,
      "apr": 0
    },
    {
      "id": "ai16z-aioraai",
      "name": "AI16Z/AIORAAI",
      "token0": "AI16Z",
      "token1": "AIORAAI",
      "tvl": 0,
      "apr": 0
    },
    {
      "id": "defai-cbtc",
      "name": "DEFAI/cBTC",
      "token0": "DEFAI",
      "token1": "cBTC",
      "tvl": 0,
      "apr": 0
    },
    {
      "id": "defai-lox",
      "name": "DEFAI/LOX",
      "token0": "DEFAI",
      "token1": "LOX",
      "tvl": 0,
      "apr": 0
    }
    
  ]
} 